parao/__init__.py
parao/_timeit.py
parao/action.py
parao/cache.py
parao/cast.py
parao/cli.py
parao/core.py
parao/misc.py
parao/output.py
parao/print.py
parao/run.py
parao/shash.py
parao/steno.py
parao/task.py
parao-0.0.9.dist-info/METADATA
parao-0.0.9.dist-info/WHEEL
parao-0.0.9.dist-info/licenses/LICENSE
parao-0.0.9.dist-info/RECORD
