Metadata-Version: 2.4
Name: parao
Version: 0.0.9
Summary: Coming soon
Author-email: "B. Fischer" <b.fis@cern.ch>
License-File: LICENSE
Requires-Python: >=3.12
